links_notation/__init__.py
links_notation/formatter.py
links_notation/link.py
links_notation/parser.py
links_notation-0.11.0.dist-info/METADATA
links_notation-0.11.0.dist-info/WHEEL
links_notation-0.11.0.dist-info/top_level.txt
links_notation-0.11.0.dist-info/RECORD
