Metadata-Version: 2.4
Name: links-notation
Version: 0.11.0
Summary: Python implementation of the Links Notation parser
Author-email: "Link.Foundation" <drakonard@gmail.com>
License: Unlicense
Project-URL: Homepage, https://github.com/link-foundation/links-notation
Project-URL: Repository, https://github.com/link-foundation/links-notation
Project-URL: Issues, https://github.com/link-foundation/links-notation/issues
Keywords: lino,parser,links,notation,protocol
Classifier: Development Status :: 4 - Beta
Classifier: Intended Audience :: Developers
Classifier: License :: Public Domain
Classifier: Programming Language :: Python :: 3
Classifier: Programming Language :: Python :: 3.13
Classifier: Topic :: Software Development :: Libraries :: Python Modules
Classifier: Topic :: Text Processing
Requires-Python: >=3.13
